emoted/__init__.py
emoted/cli.py
emoted/pi2.py
emoted-0.1.0.dist-info/licenses/LICENSE
emoted-0.1.0.dist-info/METADATA
emoted-0.1.0.dist-info/WHEEL
emoted-0.1.0.dist-info/entry_points.txt
emoted-0.1.0.dist-info/top_level.txt
emoted-0.1.0.dist-info/RECORD
