Metadata-Version: 2.4
Name: EmoTed
Version: 0.1.0
Summary: Emoted — async extension/path checker (use responsibly)
Author-email: Tuhin Khan <7uh1n1995@gmail.com>
License: MIT
Requires-Python: >=3.8
License-File: LICENSE
Requires-Dist: aiohttp>=3.8.1
Dynamic: license-file
